{
  "1": {
    "n": 1,
    "value": 1,
    "status": "PROVED",
    "elapsed": 0.001,
    "bbox": "1 x 1",
    "cells": [
      [
        0,
        0
      ]
    ],
    "grid_size": [
      1,
      1
    ],
    "num_placements": 1,
    "num_pieces": 1
  },
  "2": {
    "n": 2,
    "value": 3,
    "status": "PROVED",
    "elapsed": 0.001,
    "bbox": "2 x 2",
    "cells": [
      [
        0,
        1
      ],
      [
        1,
        0
      ],
      [
        1,
        1
      ]
    ],
    "grid_size": [
      2,
      2
    ],
    "num_placements": 4,
    "num_pieces": 2
  },
  "3": {
    "n": 3,
    "value": 5,
    "status": "PROVED",
    "elapsed": 0.001,
    "bbox": "3 x 3",
    "cells": [
      [
        0,
        1
      ],
      [
        1,
        0
      ],
      [
        1,
        1
      ],
      [
        1,
        2
      ],
      [
        2,
        1
      ]
    ],
    "grid_size": [
      3,
      3
    ],
    "num_placements": 22,
    "num_pieces": 6
  },
  "4": {
    "n": 4,
    "value": 9,
    "status": "PROVED",
    "elapsed": 0.003,
    "bbox": "4 x 4",
    "cells": [
      [
        0,
        2
      ],
      [
        1,
        1
      ],
      [
        1,
        2
      ],
      [
        2,
        0
      ],
      [
        2,
        1
      ],
      [
        2,
        2
      ],
      [
        2,
        3
      ],
      [
        3,
        1
      ],
      [
        3,
        2
      ]
    ],
    "grid_size": [
      4,
      4
    ],
    "num_placements": 113,
    "num_pieces": 19
  },
  "5": {
    "n": 5,
    "value": 13,
    "status": "PROVED",
    "elapsed": 0.01,
    "bbox": "5 x 5",
    "cells": [
      [
        0,
        2
      ],
      [
        1,
        1
      ],
      [
        1,
        2
      ],
      [
        1,
        3
      ],
      [
        2,
        0
      ],
      [
        2,
        1
      ],
      [
        2,
        2
      ],
      [
        2,
        3
      ],
      [
        2,
        4
      ],
      [
        3,
        1
      ],
      [
        3,
        2
      ],
      [
        3,
        3
      ],
      [
        4,
        2
      ]
    ],
    "grid_size": [
      5,
      5
    ],
    "num_placements": 571,
    "num_pieces": 63
  },
  "6": {
    "n": 6,
    "value": 18,
    "status": "PROVED",
    "elapsed": 0.087,
    "bbox": "6 x 6",
    "cells": [
      [
        0,
        3
      ],
      [
        1,
        2
      ],
      [
        1,
        3
      ],
      [
        2,
        1
      ],
      [
        2,
        2
      ],
      [
        2,
        3
      ],
      [
        2,
        4
      ],
      [
        2,
        5
      ],
      [
        3,
        0
      ],
      [
        3,
        1
      ],
      [
        3,
        2
      ],
      [
        3,
        3
      ],
      [
        3,
        4
      ],
      [
        3,
        5
      ],
      [
        4,
        2
      ],
      [
        4,
        3
      ],
      [
        5,
        2
      ],
      [
        5,
        3
      ]
    ],
    "grid_size": [
      6,
      6
    ],
    "num_placements": 2816,
    "num_pieces": 216
  },
  "7": {
    "n": 7,
    "value": 24,
    "status": "PROVED",
    "elapsed": 1.396,
    "bbox": "7 x 7",
    "cells": [
      [
        0,
        3
      ],
      [
        1,
        2
      ],
      [
        1,
        3
      ],
      [
        1,
        4
      ],
      [
        2,
        1
      ],
      [
        2,
        3
      ],
      [
        2,
        4
      ],
      [
        2,
        5
      ],
      [
        3,
        0
      ],
      [
        3,
        1
      ],
      [
        3,
        2
      ],
      [
        3,
        3
      ],
      [
        3,
        4
      ],
      [
        3,
        5
      ],
      [
        3,
        6
      ],
      [
        4,
        1
      ],
      [
        4,
        2
      ],
      [
        4,
        3
      ],
      [
        4,
        4
      ],
      [
        4,
        5
      ],
      [
        5,
        2
      ],
      [
        5,
        3
      ],
      [
        5,
        4
      ],
      [
        6,
        3
      ]
    ],
    "grid_size": [
      7,
      7
    ],
    "num_placements": 13616,
    "num_pieces": 760
  },
  "8": {
    "n": 8,
    "value": 31,
    "status": "PROVED",
    "elapsed": 11.094,
    "bbox": "8 x 8",
    "cells": [
      [
        0,
        4
      ],
      [
        1,
        3
      ],
      [
        1,
        4
      ],
      [
        2,
        2
      ],
      [
        2,
        3
      ],
      [
        2,
        4
      ],
      [
        2,
        5
      ],
      [
        3,
        1
      ],
      [
        3,
        2
      ],
      [
        3,
        3
      ],
      [
        3,
        4
      ],
      [
        3,
        5
      ],
      [
        3,
        6
      ],
      [
        4,
        0
      ],
      [
        4,
        1
      ],
      [
        4,
        2
      ],
      [
        4,
        3
      ],
      [
        4,
        4
      ],
      [
        4,
        5
      ],
      [
        4,
        6
      ],
      [
        4,
        7
      ],
      [
        5,
        1
      ],
      [
        5,
        2
      ],
      [
        5,
        3
      ],
      [
        5,
        4
      ],
      [
        5,
        5
      ],
      [
        5,
        6
      ],
      [
        6,
        3
      ],
      [
        6,
        4
      ],
      [
        7,
        3
      ],
      [
        7,
        4
      ]
    ],
    "grid_size": [
      8,
      8
    ],
    "num_placements": 64678,
    "num_pieces": 2725
  }
}